xbeetransmission
