Metadata-Version: 1.0
Name: xbeetransmission
Version: 0.2.2
Summary: xbeetransmission is a python module is designed to reliably and securely send messages over Xbee modules in out-of-the-box configuration.
Home-page: https://github.com/KyleEvers/xbeetransmission
Author: Kyle Evers
Author-email: kyleevers14@yahoo.com
License: MIT
Keywords: xbee
Platform: UNKNOWN
